{
  "website": "https://www.onlinegames.io",
  "extraction_timestamp": "2025-09-18 16:53:19",
  "total_games": 90,
  "games": [
    {
      "title": "Dynamons 12",
      "url": "https://www.onlinegames.io/dynamons-12/",
      "iframes": [
        {
          "src": "https://html5.gamedistribution.com/9fe4c58c9f3649798bf5cb13d6dff219/?gd_sdk_referrer_url=https:/www.onlinegames.io/dynamons-12/",
          "width": "1060",
          "height": "650",
          "frameborder": "0",
          "allowfullscreen": "allowfullscreen",
          "sandbox": ""
        }
      ],
      "description": "Catch wild Dynamons, battle masters, and build your ultimate team. Use strategy in turn-based card fights to conquer the dungeon in Dynamons 12.",
      "tags": [],
      "category": "Home",
      "rating": "",
      "play_count": "",
      "game_type": "HTML5",
      "thumbnail": "https://www.onlinegames.io/media/posts/1072/Dynamonts-12.webp",
      "thumbnail_alt": ""
    },
    {
      "title": "Street Traffic Racer",
      "url": "https://www.onlinegames.io/street-traffic-racer/",
      "iframes": [
        {
          "src": "https://html5.gamedistribution.com/b4d7df30b6354d92aad8ac6b6162dc74/?gd_sdk_referrer_url=https://www.onlinegames.io/street-traffic-racer/",
          "width": "1060",
          "height": "650",
          "frameborder": "0",
          "allowfullscreen": "allowfullscreen",
          "sandbox": ""
        }
      ],
      "description": "Race through traffic, drift past cars, and earn cash for upgrades. Customize your ride and see how far you can go without crashing!",
      "tags": [],
      "category": "Home",
      "rating": "",
      "play_count": "",
      "game_type": "HTML5",
      "thumbnail": "https://www.onlinegames.io/media/posts/1071/Street-Traffic-Racer.webp",
      "thumbnail_alt": ""
    },
    {
      "title": "Geometry Arrow 2",
      "url": "https://www.onlinegames.io/geometry-arrow-2/",
      "iframes": [
        {
          "src": "https://html5.gamedistribution.com/93ec13ded90f4ef8b46b91f7654945cd/?gd_sdk_referrer_url=https://www.onlinegames.io/geometry-arrow-2/",
          "width": "1060",
          "height": "650",
          "frameborder": "0",
          "allowfullscreen": "allowfullscreen",
          "sandbox": ""
        }
      ],
      "description": "Guide your arrow and ball through a shifting tunnel of cubes and triangles. Dodge obstacles, master portals, and conquer every level!",
      "tags": [],
      "category": "Home",
      "rating": "",
      "play_count": "",
      "game_type": "HTML5",
      "thumbnail": "https://www.onlinegames.io/media/website/online-games-io.png",
      "thumbnail_alt": "Online Games.io"
    },
    {
      "title": "Slope Run",
      "url": "https://www.onlinegames.io/slope-run/",
      "iframes": [
        {
          "src": "https://html5.gamedistribution.com/b82efa0f9d7648beb126d62c0fb9363d/?gd_sdk_referrer_url=https://www.onlinegames.io/slope-run/",
          "width": "1060",
          "height": "650",
          "frameborder": "0",
          "allowfullscreen": "allowfullscreen",
          "sandbox": ""
        }
      ],
      "description": "Roll as an astronaut in a ball through endless space tunnels in Slope Run! Dodge holes, survive unstable tiles, and reach planets to recover lost memories.",
      "tags": [],
      "category": "Home",
      "rating": "",
      "play_count": "",
      "game_type": "HTML5",
      "thumbnail": "https://www.onlinegames.io/media/posts/1069/slope-run-game.webp",
      "thumbnail_alt": ""
    },
    {
      "title": "Papa's Taco Mia",
      "url": "https://www.onlinegames.io/papas-taco-mia/",
      "iframes": [
        {
          "src": "https://cloud.onlinegames.io/games/2024/flash/papas-taco-mia/index-og.html",
          "width": "1060",
          "height": "650",
          "frameborder": "0",
          "allowfullscreen": "allowfullscreen",
          "sandbox": ""
        }
      ],
      "description": "Run Papaâs Taco Mia after winning a taco-eating contest! Serve tasty tacos, earn tips, and upgrade your shop into the spiciest spot in town.",
      "tags": [],
      "category": "Home",
      "rating": "",
      "play_count": "",
      "game_type": "Flash",
      "thumbnail": "https://www.onlinegames.io/media/posts/1068/papas-taco-mia.webp",
      "thumbnail_alt": ""
    },
    {
      "title": "Papa's Donuteria",
      "url": "https://www.onlinegames.io/papas-donuteria/",
      "iframes": [
        {
          "src": "https://cloud.onlinegames.io/games/2024/flash/papas-donuteria/index-og.html ",
          "width": "1060",
          "height": "650",
          "frameborder": "0",
          "allowfullscreen": "allowfullscreen",
          "sandbox": ""
        }
      ],
      "description": "Cook and serve donuts in Papaâs Donuteria! Unlock ingredients, please picky eaters, and build the sweetest shop in the amusement park.",
      "tags": [],
      "category": "Home",
      "rating": "",
      "play_count": "",
      "game_type": "Flash",
      "thumbnail": "https://www.onlinegames.io/media/posts/1067/papas-donuteria.webp",
      "thumbnail_alt": ""
    },
    {
      "title": "Italian Brainrot Survive Parkour",
      "url": "https://www.onlinegames.io/italian-brainrot-survive-parkour/",
      "iframes": [
        {
          "src": "https://html5.gamedistribution.com/5c5b89d12e404bf6a4979ae0c0c9a09c/?gd_sdk_referrer_url=https://www.onlinegames.io/italian-brainrot-survive-parkour/ ",
          "width": "1060",
          "height": "650",
          "frameborder": "0",
          "allowfullscreen": "allowfullscreen",
          "sandbox": ""
        }
      ],
      "description": "Are you silly enough to survive the madness? Run, jump & embrace chaos in Italian Brainrot Survive Parkour. Fail funny, survive sillier!",
      "tags": [],
      "category": "Home",
      "rating": "",
      "play_count": "",
      "game_type": "HTML5",
      "thumbnail": "https://www.onlinegames.io/media/posts/1066/italian-brainrot-survive-parkour-game.webp",
      "thumbnail_alt": ""
    },
    {
      "title": "Brainrot Clicker",
      "url": "https://www.onlinegames.io/brainrot-clicker/",
      "iframes": [
        {
          "src": "https://html5.gamedistribution.com/eb45cb884a3140bea17b3070ff6b4d70/?gd_sdk_referrer_url=https://www.onlinegames.io/brainrot-clicker/",
          "width": "1060",
          "height": "650",
          "frameborder": "0",
          "allowfullscreen": "allowfullscreen",
          "sandbox": ""
        }
      ],
      "description": "Brainrot Clicker delivers endless fun with Italian vibes and silly AI creatures. Click, unlock boosters, and challenge friends in this wacky game!",
      "tags": [],
      "category": "Home",
      "rating": "",
      "play_count": "",
      "game_type": "HTML5",
      "thumbnail": "https://www.onlinegames.io/media/posts/1065/brainrot-clicker-game.webp",
      "thumbnail_alt": ""
    },
    {
      "title": "Guess the Italian Brainrot Animals",
      "url": "https://www.onlinegames.io/guess-the-italian-brainrot-animals/",
      "iframes": [
        {
          "src": "https://html5.gamedistribution.com/485ace88aed344f8b2ff6821a46e4431/?gd_sdk_referrer_url=https://www.onlinegames.io/guess-the-italian-brainrot-animals/ ",
          "width": "1060",
          "height": "650",
          "frameborder": "0",
          "allowfullscreen": "allowfullscreen",
          "sandbox": ""
        }
      ],
      "description": "Guess the Italian Brainrot Animals: a wild meme quiz of AI-made TikTok celebs with absurd emoji mashups. Fun, weird, nonstop guessing!",
      "tags": [],
      "category": "Home",
      "rating": "",
      "play_count": "",
      "game_type": "HTML5",
      "thumbnail": "https://www.onlinegames.io/media/posts/1064/guess-the-italian-brainrot-animals-game.webp",
      "thumbnail_alt": ""
    },
    {
      "title": "Cosmo Void",
      "url": "https://www.onlinegames.io/cosmo-void/",
      "iframes": [
        {
          "src": "https://html5.gamedistribution.com/f30771a05eb84a67a794e85bc39621e7/?gd_sdk_referrer_url=https://www.onlinegames.io/cosmo-void/ ",
          "width": "1060",
          "height": "650",
          "frameborder": "0",
          "allowfullscreen": "allowfullscreen",
          "sandbox": ""
        }
      ],
      "description": "Pilot a futuristic spacecraft through the endless void. Avoid shifting obstacles, test your reflexes, and see if you can survive the cosmic challenge!",
      "tags": [],
      "category": "Home",
      "rating": "",
      "play_count": "",
      "game_type": "HTML5",
      "thumbnail": "https://www.onlinegames.io/media/posts/1063/cosmo-void.webp",
      "thumbnail_alt": ""
    },
    {
      "title": "Labubu Merge",
      "url": "https://www.onlinegames.io/labubu-merge/",
      "iframes": [
        {
          "src": "https://html5.gamedistribution.com/f4cd70935a644d7daae05b2b4db64807/?gd_sdk_referrer_url=https://www.onlinegames.io/labubu-merge/ ",
          "width": "1060",
          "height": "650",
          "frameborder": "0",
          "allowfullscreen": "allowfullscreen",
          "sandbox": ""
        }
      ],
      "description": "Merge mischievous Labubus to unlock cute yet creepy plushies! Grow your cuddly-creepy crew and be on trend with Labubu Merge!",
      "tags": [],
      "category": "Home",
      "rating": "",
      "play_count": "",
      "game_type": "HTML5",
      "thumbnail": "https://www.onlinegames.io/media/posts/1062/labubu-merge-game.webp",
      "thumbnail_alt": ""
    },
    {
      "title": "Obby Gym Simulator",
      "url": "https://www.onlinegames.io/obby-gym-simulator/",
      "iframes": [
        {
          "src": "https://html5.gamedistribution.com/4a198f856f07451bb7418eae9a0c4112/?gd_sdk_referrer_url=https://www.onlinegames.io/obby-gym-simulator/",
          "width": "1060",
          "height": "650",
          "frameborder": "0",
          "allowfullscreen": "allowfullscreen",
          "sandbox": ""
        }
      ],
      "description": "Train hard in Obby Gym Simulator! Bulk up, fight monsters, earn trophies, and escape the prison in this fun gym-prison adventure.",
      "tags": [],
      "category": "Home",
      "rating": "",
      "play_count": "",
      "game_type": "HTML5",
      "thumbnail": "https://www.onlinegames.io/media/posts/1061/obby-gym-simulator.webp",
      "thumbnail_alt": ""
    },
    {
      "title": "Waterpark Slide io",
      "url": "https://www.onlinegames.io/waterpark-slide-io/",
      "iframes": [
        {
          "src": "https://cloud.onlinegames.io/games/2022/unity3/waterpark-slide-io/index-og.html",
          "width": "1060",
          "height": "650",
          "frameborder": "0",
          "allowfullscreen": "allowfullscreen",
          "sandbox": ""
        }
      ],
      "description": "Race down vibrant water slides in Waterpark Slide io! Slide, boost, and outplay players or bots in the silliest, most colorful summer adventure.",
      "tags": [],
      "category": "Home",
      "rating": "",
      "play_count": "",
      "game_type": "Unity",
      "thumbnail": "https://www.onlinegames.io/media/posts/1060/waterpark-slide-io.webp",
      "thumbnail_alt": ""
    },
    {
      "title": "Obby Survive Parkour",
      "url": "https://www.onlinegames.io/obby-survive-parkour/",
      "iframes": [
        {
          "src": "https://html5.gamedistribution.com/9423ba1c5c0847998ae6bbae78ba4c91/?gd_sdk_referrer_url=https://www.onlinegames.io/obby-survive-parkour/",
          "width": "1060",
          "height": "650",
          "frameborder": "0",
          "allowfullscreen": "allowfullscreen",
          "sandbox": ""
        }
      ],
      "description": "Obby Survive Parkour: run, jump, and survive thrilling obstacle courses solo or with a friend. One wrong move and itâs game over!",
      "tags": [],
      "category": "Home",
      "rating": "",
      "play_count": "",
      "game_type": "HTML5",
      "thumbnail": "https://www.onlinegames.io/media/posts/1059/obby-survive-parkour.webp",
      "thumbnail_alt": ""
    },
    {
      "title": "JailBreak Prison EscapeÂ",
      "url": "https://www.onlinegames.io/jailbreak-prison-escape/",
      "iframes": [
        {
          "src": "https://html5.gamedistribution.com/e5c41772e13f49d891a9bff3ea726943/?gd_sdk_referrer_url=https://www.onlinegames.io/jailbreak-prison-escape/",
          "width": "1060",
          "height": "650",
          "frameborder": "0",
          "allowfullscreen": "allowfullscreen",
          "sandbox": ""
        }
      ],
      "description": "Test your wits in JailBreak Prison Escape! Outsmart guards, solve puzzles, and sneak your way to freedom in the ultimate escape challenge.",
      "tags": [],
      "category": "Home",
      "rating": "",
      "play_count": "",
      "game_type": "HTML5",
      "thumbnail": "https://www.onlinegames.io/media/posts/1058/jailbreak-prison-escape.webp",
      "thumbnail_alt": ""
    },
    {
      "title": "Merge Brainrot",
      "url": "https://www.onlinegames.io/merge-brainrot/",
      "iframes": [
        {
          "src": "https://html5.gamedistribution.com/ea08335b6c9043e7a2403f6d5e8d1664/?gd_sdk_referrer_url=https://www.onlinegames.io/merge-brainrot/",
          "width": "1060",
          "height": "650",
          "frameborder": "0",
          "allowfullscreen": "allowfullscreen",
          "sandbox": ""
        }
      ],
      "description": "Merge Brainrot: Drop, merge & unlock absurd Italian meme critters in a wacky physics game. Donât overflow the tank â¼ get brain-rotted!",
      "tags": [],
      "category": "Home",
      "rating": "",
      "play_count": "",
      "game_type": "HTML5",
      "thumbnail": "https://www.onlinegames.io/media/posts/1057/merge-brainrot.webp",
      "thumbnail_alt": ""
    },
    {
      "title": "Drift King",
      "url": "https://www.onlinegames.io/drift-king/",
      "iframes": [
        {
          "src": "https://www.onlinegames.io/games/2024/unity/drift-king/index.html",
          "width": "1060",
          "height": "650",
          "frameborder": "0",
          "allowfullscreen": "allowfullscreen",
          "sandbox": ""
        }
      ],
      "description": "Race with each other, make drifting competitions or chase after each other to experience crashes and chaos. in Drift King, free online game!",
      "tags": [],
      "category": "Home",
      "rating": "",
      "play_count": "",
      "game_type": "Unity",
      "thumbnail": "https://www.onlinegames.io/media/posts/729/Drift-King.jpg",
      "thumbnail_alt": ""
    },
    {
      "title": "Geometry Arrow",
      "url": "https://www.onlinegames.io/geometry-arrow/",
      "iframes": [
        {
          "src": "https://html5.gamedistribution.com/9ee26ba4405c456094c70af7dc31a524/?gd_sdk_referrer_url=https://www.onlinegames.io/geometry-arrow/",
          "width": "1060",
          "height": "650",
          "frameborder": "0",
          "allowfullscreen": "allowfullscreen",
          "sandbox": ""
        }
      ],
      "description": "Guide your arrow through 13 levels and secret tunnels in Geometry Arrow. This free online browser game delivers rhythmic platform thrills. Play now!",
      "tags": [],
      "category": "Home",
      "rating": "",
      "play_count": "",
      "game_type": "HTML5",
      "thumbnail": "https://www.onlinegames.io/media/website/online-games-io.png",
      "thumbnail_alt": "Online Games.io"
    },
    {
      "title": "Bloxd io",
      "url": "https://www.onlinegames.io/bloxd-io/",
      "iframes": [
        {
          "src": "https://bloxd.io/",
          "width": "1060",
          "height": "650",
          "frameborder": "0",
          "allowfullscreen": "allowfullscreen",
          "sandbox": ""
        }
      ],
      "description": "Welcome to Bloxd io, an ultimate online Minecraft game with diverse modes. Whether you're interested in a peaceful building session or intense PvP battles, you will find what you expect from Bloxd io.",
      "tags": [],
      "category": "Home",
      "rating": "",
      "play_count": "",
      "game_type": "Web",
      "thumbnail": "https://www.onlinegames.io/media/posts/722/Bloxd-io-Play.jpg",
      "thumbnail_alt": ""
    },
    {
      "title": "Italian Brainrot Clicker",
      "url": "https://www.onlinegames.io/italian-brainrot-clicker/",
      "iframes": [
        {
          "src": "https://html5.gamedistribution.com/fd1a94ebbb2141d1adf2d9e3629abcf3/?gd_sdk_referrer_url=https://www.onlinegames.io/italian-brainrot-clicker/",
          "width": "1060",
          "height": "650",
          "frameborder": "0",
          "allowfullscreen": "allowfullscreen",
          "sandbox": ""
        }
      ],
      "description": "Unleash chaos in this hilarious Italian Brainrot clicker game! Unlock wild skins, power-ups, and leaderboards in this stress-melting tap frenzy.",
      "tags": [],
      "category": "Home",
      "rating": "",
      "play_count": "",
      "game_type": "HTML5",
      "thumbnail": "https://www.onlinegames.io/media/posts/1046/italian_brainrot_clicker_game.webp",
      "thumbnail_alt": ""
    },
    {
      "title": "Drift Hunters 2",
      "url": "https://www.onlinegames.io/drift-hunters-2/",
      "iframes": [
        {
          "src": "https://www.onlinegames.io/games/2024/unity/drift-hunters-2/index.html",
          "width": "1060",
          "height": "650",
          "frameborder": "0",
          "allowfullscreen": "allowfullscreen",
          "sandbox": ""
        }
      ],
      "description": "Drift Hunters 2 is a web-based driving game with premium 3D graphics and realistic physics. Play now on OnlineGames.io!",
      "tags": [],
      "category": "Home",
      "rating": "",
      "play_count": "",
      "game_type": "Unity",
      "thumbnail": "https://www.onlinegames.io/media/posts/669/Drift-Hunters-2-Online.jpg",
      "thumbnail_alt": ""
    },
    {
      "title": "Run 3",
      "url": "https://www.onlinegames.io/run-3/",
      "iframes": [
        {
          "src": "https://cloud.onlinegames.io/games/2025/more/run-3/index-og.html",
          "width": "1060",
          "height": "650",
          "frameborder": "0",
          "allowfullscreen": "allowfullscreen",
          "sandbox": ""
        }
      ],
      "description": "Guide an alien through gravity-defying tunnels in space, dodging gaps and obstacles in the thrilling endless platformer Run 3.",
      "tags": [],
      "category": "Home",
      "rating": "",
      "play_count": "",
      "game_type": "Web",
      "thumbnail": "https://www.onlinegames.io/media/posts/1056/run-3-online.webp",
      "thumbnail_alt": ""
    },
    {
      "title": "Highway Traffic",
      "url": "https://www.onlinegames.io/highway-traffic/",
      "iframes": [
        {
          "src": "https://www.onlinegames.io/games/2022/unity/highway-traffic/index.html",
          "width": "1060",
          "height": "650",
          "frameborder": "0",
          "allowfullscreen": "allowfullscreen",
          "sandbox": ""
        }
      ],
      "description": "Highway TrafficÂ game is centered around driving down the highway, dodging other cars, and avoiding accidents. It gets tricky because other…",
      "tags": [],
      "category": "Home",
      "rating": "",
      "play_count": "",
      "game_type": "Unity",
      "thumbnail": "https://www.onlinegames.io/media/posts/32/Highway-Traffic-2.jpg",
      "thumbnail_alt": ""
    },
    {
      "title": "Traffic Jam 3D",
      "url": "https://www.onlinegames.io/traffic-jam-3d/",
      "iframes": [
        {
          "src": "https://html5.gamedistribution.com/337302b23b5943d8bcfc501d81d50cdb/?gd_sdk_referrer_url=https://www.onlinegames.io/traffic-jam-3d/",
          "width": "1060",
          "height": "650",
          "frameborder": "0",
          "allowfullscreen": "allowfullscreen",
          "sandbox": ""
        }
      ],
      "description": "Steer your car on the highway at full speed without crashing any other vehicle in Traffic Jam 3D, a driving in traffic game. Set your racing scenario as you wish!",
      "tags": [],
      "category": "Home",
      "rating": "",
      "play_count": "",
      "game_type": "HTML5",
      "thumbnail": "https://www.onlinegames.io/media/posts/784/Traffic-Jam.jpg",
      "thumbnail_alt": ""
    },
    {
      "title": "Love Tester",
      "url": "https://www.onlinegames.io/love-tester/",
      "iframes": [
        {
          "src": "https://www.onlinegames.io/games/2021/3/love-tester/index.html",
          "width": "1060",
          "height": "650",
          "frameborder": "0",
          "allowfullscreen": "allowfullscreen",
          "sandbox": ""
        }
      ],
      "description": "Do you want to know how much your crush falls for you? Here is a way to test the love…",
      "tags": [],
      "category": "Home",
      "rating": "",
      "play_count": "",
      "game_type": "Web",
      "thumbnail": "https://www.onlinegames.io/media/posts/152/love-tester.jpg",
      "thumbnail_alt": ""
    },
    {
      "title": "Obby But You're on a Bike",
      "url": "https://www.onlinegames.io/obby-but-you-re-on-a-bike/",
      "iframes": [
        {
          "src": "https://playhop.com/app/257923?utm_source=distrib&is-united-page=1&skip-guard=1&header=no&utm_medium=cristian-ovidiu&clid=8531463",
          "width": "1060",
          "height": "650",
          "frameborder": "0",
          "allowfullscreen": "allowfullscreen",
          "sandbox": ""
        }
      ],
      "description": "Ride through wild 3D platforming levels in Obby but Youâre on a Bike! Capture flags, upgrade your bike, and test your skills. Play now on OnlineGames.io!",
      "tags": [],
      "category": "Home",
      "rating": "",
      "play_count": "",
      "game_type": "Web",
      "thumbnail": "https://www.onlinegames.io/media/posts/885/obby-but-your-on-a-bike.jpg",
      "thumbnail_alt": ""
    },
    {
      "title": "Miniblox io",
      "url": "https://www.onlinegames.io/miniblox-io/",
      "iframes": [
        {
          "src": "https://miniblox.io/",
          "width": "1060",
          "height": "650",
          "frameborder": "0",
          "allowfullscreen": "allowfullscreen",
          "sandbox": ""
        }
      ],
      "description": "Miniblox io, a fantastic sandbox game, allows you to define your own gaming experience. Play with online players across the world and enjoy the game!",
      "tags": [],
      "category": "Home",
      "rating": "",
      "play_count": "",
      "game_type": "Web",
      "thumbnail": "https://www.onlinegames.io/media/posts/595/MiniBlox.io.jpg",
      "thumbnail_alt": ""
    },
    {
      "title": "Pixel Path",
      "url": "https://www.onlinegames.io/pixel-path/",
      "iframes": [
        {
          "src": "https://html5.gamedistribution.com/3ffc5c0944f54f06afb212ca7d80bb00/?gd_sdk_referrer_url=https://www.onlinegames.io/pixel-path/",
          "width": "1060",
          "height": "650",
          "frameborder": "0",
          "allowfullscreen": "allowfullscreen",
          "sandbox": ""
        }
      ],
      "description": "Guide your pixel hero through 50 tricky levels filled with traps, surprises, and evolving mechanics in this fast-paced retro platformer.",
      "tags": [],
      "category": "Home",
      "rating": "",
      "play_count": "",
      "game_type": "HTML5",
      "thumbnail": "https://www.onlinegames.io/media/posts/1050/pixel_path_game.webp",
      "thumbnail_alt": ""
    },
    {
      "title": "Life Simulator",
      "url": "https://www.onlinegames.io/life-simulator/",
      "iframes": [
        {
          "src": "https://html5.gamedistribution.com/ac6a950a44d144139dabe7837aa4aab9/?gd_sdk_referrer_url=https://www.onlinegames.io/bitlife",
          "width": "1060",
          "height": "650",
          "frameborder": "0",
          "allowfullscreen": "allowfullscreen",
          "sandbox": ""
        }
      ],
      "description": "",
      "tags": [],
      "category": "Home",
      "rating": "",
      "play_count": "",
      "game_type": "HTML5",
      "thumbnail": "https://www.onlinegames.io/media/posts/998/life-simulator.jpg",
      "thumbnail_alt": ""
    },
    {
      "title": "Geometry Dash",
      "url": "https://www.onlinegames.io/geometry-dash/",
      "iframes": [
        {
          "src": "https://turbowarp.org/105500895/embed?autoplay&addons=remove-curved-stage-border",
          "width": "1060",
          "height": "650",
          "frameborder": "0",
          "allowfullscreen": "allowfullscreen",
          "sandbox": ""
        }
      ],
      "description": "Prepare yourself for the hardest! Geometry Dash is a very challenging arcade game, and it is famous all over the…",
      "tags": [],
      "category": "Home",
      "rating": "",
      "play_count": "",
      "game_type": "Web",
      "thumbnail": "https://www.onlinegames.io/media/posts/411/Geometry-Dash.jpg",
      "thumbnail_alt": ""
    },
    {
      "title": "Stack Fire Ball",
      "url": "https://www.onlinegames.io/stack-fire-ball/",
      "iframes": [
        {
          "src": "https://www.onlinegames.io/games/2021/unity/stack-fire-ball/index.html",
          "width": "1060",
          "height": "650",
          "frameborder": "0",
          "allowfullscreen": "allowfullscreen",
          "sandbox": ""
        }
      ],
      "description": "Reach the end by guiding the ball through each stage, avoiding the dark tiles. This game is a combination between…",
      "tags": [],
      "category": "Home",
      "rating": "",
      "play_count": "",
      "game_type": "Unity",
      "thumbnail": "https://www.onlinegames.io/media/posts/184/Stack-Fire-Ball-Game.jpg",
      "thumbnail_alt": ""
    },
    {
      "title": "Masked Special Forces",
      "url": "https://www.onlinegames.io/masked-special-forces/",
      "iframes": [
        {
          "src": "https://www.onlinegames.io/games/2022/unity2/masked-special-forces/index.html",
          "width": "1060",
          "height": "650",
          "frameborder": "0",
          "allowfullscreen": "allowfullscreen",
          "sandbox": ""
        }
      ],
      "description": "Masked Special Forces is a multiplayer first-person shooter game. As a talented warrior, team up, strategize, and take down the opponents one by one.",
      "tags": [],
      "category": "Home",
      "rating": "",
      "play_count": "",
      "game_type": "Unity",
      "thumbnail": "https://www.onlinegames.io/media/posts/310/Masked-Special-Forces-FPS.jpg",
      "thumbnail_alt": ""
    },
    {
      "title": "GTA Simulator",
      "url": "https://www.onlinegames.io/gta-simulator/",
      "iframes": [
        {
          "src": "https://www.onlinegames.io/games/2023/unity2/gta-simulator/index.html",
          "width": "1060",
          "height": "650",
          "frameborder": "0",
          "allowfullscreen": "allowfullscreen",
          "sandbox": ""
        }
      ],
      "description": "You know that famous GTA video game series, right? Well, meet its online and free version on OnlineGames.io. GTA Simulator…",
      "tags": [],
      "category": "Home",
      "rating": "",
      "play_count": "",
      "game_type": "Unity",
      "thumbnail": "https://www.onlinegames.io/media/posts/416/GTA-Simulator.jpg",
      "thumbnail_alt": ""
    },
    {
      "title": "Fragen",
      "url": "https://www.onlinegames.io/fragen/",
      "iframes": [
        {
          "src": "https://html5.gamedistribution.com/626030ce36a249729e19df483d7836dc/?gd_sdk_referrer_url=https://www.onlinegames.io/fragen/",
          "width": "1060",
          "height": "650",
          "frameborder": "0",
          "allowfullscreen": "allowfullscreen",
          "sandbox": ""
        }
      ],
      "description": "Jump into Fragen, a fast-paced FPS packed with action, strategy, daily rewards, and customizable gear. Play solo or in teams and dominate the battlefield!",
      "tags": [],
      "category": "Home",
      "rating": "",
      "play_count": "",
      "game_type": "HTML5",
      "thumbnail": "https://www.onlinegames.io/media/posts/1040/fragen-game.webp",
      "thumbnail_alt": ""
    },
    {
      "title": "Flip Bottle",
      "url": "https://www.onlinegames.io/flip-bottle/",
      "iframes": [
        {
          "src": "https://html5.gamedistribution.com/95c4932d8f6d42688b0fa38274282a86/?gd_sdk_referrer_url=https://www.onlinegames.io/flip-bottle/",
          "width": "1060",
          "height": "650",
          "frameborder": "0",
          "allowfullscreen": "allowfullscreen",
          "sandbox": ""
        }
      ],
      "description": "Flip Bottle is a physics-based platformer where you flip bottle across obstacles, earn coins, and master perfect landings!",
      "tags": [],
      "category": "Home",
      "rating": "",
      "play_count": "",
      "game_type": "HTML5",
      "thumbnail": "https://www.onlinegames.io/media/posts/1052/flip_bottle_game.webp",
      "thumbnail_alt": ""
    },
    {
      "title": "Five Nights At Freddys",
      "url": "https://www.onlinegames.io/five-nights-at-freddys/",
      "iframes": [
        {
          "src": "https://www.onlinegames.io/games/2024/w1/five-nights-at-freddys/index.html",
          "width": "1060",
          "height": "650",
          "frameborder": "0",
          "allowfullscreen": "allowfullscreen",
          "sandbox": ""
        }
      ],
      "description": "Monitor the security cameras from midnight to six in the morning as a security guard in FNAF, a 2D action game. Guard yourself from the animatronics!",
      "tags": [],
      "category": "Home",
      "rating": "",
      "play_count": "",
      "game_type": "Web",
      "thumbnail": "https://www.onlinegames.io/media/posts/761/Play-FNAF-Online.jpg",
      "thumbnail_alt": ""
    },
    {
      "title": "Extreme Run 3D",
      "url": "https://www.onlinegames.io/extreme-run-3d/",
      "iframes": [
        {
          "src": "https://html5.gamedistribution.com/332fed0d374c4401934cf5b19b7a85b1/?gd_sdk_referrer_url=https://www.onlinegames.io/extreme-run-3d/",
          "width": "1060",
          "height": "650",
          "frameborder": "0",
          "allowfullscreen": "allowfullscreen",
          "sandbox": ""
        }
      ],
      "description": "Take control of a rolling ball and face various obstacles as you race through 11 levels. Start playing Extreme Run 3D now!",
      "tags": [],
      "category": "Home",
      "rating": "",
      "play_count": "",
      "game_type": "HTML5",
      "thumbnail": "https://www.onlinegames.io/media/posts/839/Extreme-Run-3D.jpg",
      "thumbnail_alt": ""
    },
    {
      "title": "Real Flight Simulator",
      "url": "https://www.onlinegames.io/real-flight-simulator/",
      "iframes": [
        {
          "src": "https://cloud.onlinegames.io/games/2023/unity2/real-flight-simulator/index.html",
          "width": "1060",
          "height": "650",
          "frameborder": "0",
          "allowfullscreen": "allowfullscreen",
          "sandbox": ""
        }
      ],
      "description": "Real Flight Simulator is a realistic game that gives you the ultimate flight experience. There is the possibility to choose…",
      "tags": [],
      "category": "Home",
      "rating": "",
      "play_count": "",
      "game_type": "Unity",
      "thumbnail": "https://www.onlinegames.io/media/posts/342/Real-Flight-Simulator-2.jpg",
      "thumbnail_alt": ""
    },
    {
      "title": "Golf Orbit",
      "url": "https://www.onlinegames.io/golf-orbit/",
      "iframes": [
        {
          "src": "https://html5.gamedistribution.com/02ff01e6e9f7451ba28d889a2a55eec9/?gd_sdk_referrer_url=https://www.onlinegames.io/golf-orbit/",
          "width": "1060",
          "height": "650",
          "frameborder": "0",
          "allowfullscreen": "allowfullscreen",
          "sandbox": ""
        }
      ],
      "description": "Play Golf Orbit online for free! Time your shots perfectly, launch the ball far, and upgrade your golfer to reach new distances.",
      "tags": [],
      "category": "Home",
      "rating": "",
      "play_count": "",
      "game_type": "HTML5",
      "thumbnail": "https://www.onlinegames.io/media/posts/953/Golf-Orbit-Play-Online.jpg",
      "thumbnail_alt": ""
    },
    {
      "title": "Skribblio",
      "url": "https://www.onlinegames.io/skribblio/",
      "iframes": [
        {
          "src": "https://skribbl.io/",
          "width": "1060",
          "height": "650",
          "frameborder": "0",
          "allowfullscreen": "allowfullscreen",
          "sandbox": ""
        }
      ],
      "description": "Scribble, scribble, scribble!âââSkribblio is a great online game for word game lovers with extensive drawing skills. Draw the given word,…",
      "tags": [],
      "category": "Home",
      "rating": "",
      "play_count": "",
      "game_type": "Web",
      "thumbnail": "https://www.onlinegames.io/media/posts/385/Skribblio.jpg",
      "thumbnail_alt": ""
    },
    {
      "title": "Idle Breakout",
      "url": "https://www.onlinegames.io/idle-breakout/",
      "iframes": [
        {
          "src": "https://www.onlinegames.io/games/2024/more/idle-breakout/index.html",
          "width": "1060",
          "height": "650",
          "frameborder": "0",
          "allowfullscreen": "allowfullscreen",
          "sandbox": ""
        }
      ],
      "description": "Idle Breakout is a free online clicker game with arcade mechanics. Start breaking bricks, now!",
      "tags": [],
      "category": "Home",
      "rating": "",
      "play_count": "",
      "game_type": "Web",
      "thumbnail": "https://www.onlinegames.io/media/posts/692/Play-Idle-Breakout.jpg",
      "thumbnail_alt": ""
    },
    {
      "title": "Checkout Frenzy",
      "url": "https://www.onlinegames.io/checkout-frenzy/",
      "iframes": [
        {
          "src": "https://cloud.onlinegames.io/games/2025/unity/checkout-frenzy/index-og.html",
          "width": "1060",
          "height": "650",
          "frameborder": "0",
          "allowfullscreen": "allowfullscreen",
          "sandbox": ""
        }
      ],
      "description": "Play Checkout Frenzy online, a cashier and store management game. Run your own store full of beeps, scans, and shopping chaos!",
      "tags": [],
      "category": "Home",
      "rating": "",
      "play_count": "",
      "game_type": "Unity",
      "thumbnail": "https://www.onlinegames.io/media/posts/974/checkout-frenzy-cashier-game.jpg",
      "thumbnail_alt": ""
    },
    {
      "title": "Tribals io",
      "url": "https://www.onlinegames.io/tribals-io/",
      "iframes": [
        {
          "src": "https://tribals.io/",
          "width": "1060",
          "height": "650",
          "frameborder": "0",
          "allowfullscreen": "allowfullscreen",
          "sandbox": ""
        }
      ],
      "description": "Survive as a caveman on an island in the Tribals io, a multiplayer survival game. Craft, build, and team up with others now!",
      "tags": [],
      "category": "Home",
      "rating": "",
      "play_count": "",
      "game_type": "Web",
      "thumbnail": "https://www.onlinegames.io/media/posts/640/Tribals.io.jpg",
      "thumbnail_alt": ""
    },
    {
      "title": "Obby Bike Trials",
      "url": "https://www.onlinegames.io/obby-bike-trials/",
      "iframes": [
        {
          "src": "https://html5.gamedistribution.com/bc2f52c2d9d04e41aee48bef01075d22/?gd_sdk_referrer_url=https://www.onlinegames.io/obby-bike-trials/",
          "width": "1060",
          "height": "650",
          "frameborder": "0",
          "allowfullscreen": "allowfullscreen",
          "sandbox": ""
        }
      ],
      "description": "Jump, race, and ride across wild floating platforms in Obby Bike Trials! Customize your rider, unlock bikes, and play solo or with a friend in 3 game modes!",
      "tags": [],
      "category": "Home",
      "rating": "",
      "play_count": "",
      "game_type": "HTML5",
      "thumbnail": "https://www.onlinegames.io/media/posts/1038/obby-bike-trials-game-4.webp",
      "thumbnail_alt": ""
    },
    {
      "title": "Drift Boss",
      "url": "https://www.onlinegames.io/drift-boss/",
      "iframes": [
        {
          "src": "https://www.onlinegames.io/games/2023/mjs/drift-boss/index.html",
          "width": "1060",
          "height": "650",
          "frameborder": "0",
          "allowfullscreen": "allowfullscreen",
          "sandbox": ""
        }
      ],
      "description": "Say hi to an easily controlled and captivating game! Drift Boss is a 3D driving game where you steer your…",
      "tags": [],
      "category": "Home",
      "rating": "",
      "play_count": "",
      "game_type": "Web",
      "thumbnail": "https://www.onlinegames.io/media/posts/378/Drift-Boss-Game.jpg",
      "thumbnail_alt": ""
    },
    {
      "title": "Drift Hunters Pro",
      "url": "https://www.onlinegames.io/drift-hunters-pro/",
      "iframes": [
        {
          "src": "https://www.onlinegames.io/games/2023/unity/drift-hunters-pro/index.html",
          "width": "1060",
          "height": "650",
          "frameborder": "0",
          "allowfullscreen": "allowfullscreen",
          "sandbox": ""
        }
      ],
      "description": "Can you hear the engine moaning? Drift Hunters Pro is a thrilling 3D game with high-quality graphics for those who…",
      "tags": [],
      "category": "Home",
      "rating": "",
      "play_count": "",
      "game_type": "Unity",
      "thumbnail": "https://www.onlinegames.io/media/posts/397/Drift-Hunters-Pro.jpg",
      "thumbnail_alt": ""
    },
    {
      "title": "Hole Digger",
      "url": "https://www.onlinegames.io/hole-digger/",
      "iframes": [
        {
          "src": "https://html5.gamedistribution.com/ddcd71fc39e745e28274a32671c254d3/?gd_sdk_referrer_url=https://www.onlinegames.io/hole-digger/",
          "width": "1060",
          "height": "650",
          "frameborder": "0",
          "allowfullscreen": "allowfullscreen",
          "sandbox": ""
        }
      ],
      "description": "Play Hole Digger, a free online simulation game where you dig for resources and treasures. Upgrade tools and explore the underground!",
      "tags": [],
      "category": "Home",
      "rating": "",
      "play_count": "",
      "game_type": "HTML5",
      "thumbnail": "https://www.onlinegames.io/media/posts/1044/hole_digger_game-2.webp",
      "thumbnail_alt": ""
    },
    {
      "title": "Unpacking",
      "url": "https://www.onlinegames.io/unpacking/",
      "iframes": [
        {
          "src": "https://html5.gamedistribution.com/d445590892294eebb41d983e1c598ab1/?gd_sdk_referrer_url=https://www.onlinegames.io/unpacking",
          "width": "1060",
          "height": "650",
          "frameborder": "0",
          "allowfullscreen": "allowfullscreen",
          "sandbox": ""
        }
      ],
      "description": "Hey there, neat freaks! We are offering you a great mess to tidy up!Â Unpacking is a free online home decoration…",
      "tags": [],
      "category": "Home",
      "rating": "",
      "play_count": "",
      "game_type": "HTML5",
      "thumbnail": "https://www.onlinegames.io/media/posts/481/Unpacking.jpg",
      "thumbnail_alt": ""
    },
    {
      "title": "Mega Lamba Ramp",
      "url": "https://www.onlinegames.io/mega-lamba-ramp/",
      "iframes": [
        {
          "src": "https://html5.gamedistribution.com/08f7196aa8c241dc81f27f118fa1f61e/?gd_sdk_referrer_url=https://www.onlinegames.io/mega-lamba-ramp/",
          "width": "1060",
          "height": "650",
          "frameborder": "0",
          "allowfullscreen": "allowfullscreen",
          "sandbox": ""
        }
      ],
      "description": "Play Mega Lamba Ramp, a free stunt-driving game where you launch cars off sky-high ramps, drift through cities, and unlock wild characters and vehicles.",
      "tags": [],
      "category": "Home",
      "rating": "",
      "play_count": "",
      "game_type": "HTML5",
      "thumbnail": "https://www.onlinegames.io/media/posts/1042/mega_lamba_ramp_game-4.webp",
      "thumbnail_alt": ""
    },
    {
      "title": "TB World",
      "url": "https://www.onlinegames.io/tb-world/",
      "iframes": [
        {
          "src": "https://playhop.com/app/364663?utm_source=distrib&is-united-page=1&skip-guard=1&header=no&utm_medium=cristian-ovidiu&clid=8531463",
          "width": "1060",
          "height": "650",
          "frameborder": "0",
          "allowfullscreen": "allowfullscreen",
          "sandbox": ""
        }
      ],
      "description": "Create your dream world in TB World, all items unlocked version of Toca Boca! Design characters, decorate homes, and play for free on OnlineGames.io!",
      "tags": [],
      "category": "Home",
      "rating": "",
      "play_count": "",
      "game_type": "Web",
      "thumbnail": "https://www.onlinegames.io/media/posts/948/TB-World-Toca-Boca.jpg",
      "thumbnail_alt": ""
    },
    {
      "title": "Aventador Vice Crime City",
      "url": "https://www.onlinegames.io/aventador-vice-crime-city/",
      "iframes": [
        {
          "src": "https://html5.gamedistribution.com/be4f7b9d1f3c4370a27cd86ba14fe15e/?gd_sdk_referrer_url=https://www.onlinegames.io/aventador-vice-crime-city/",
          "width": "1060",
          "height": "650",
          "frameborder": "0",
          "allowfullscreen": "allowfullscreen",
          "sandbox": ""
        }
      ],
      "description": "Race, drift, stunt, and escape police in Aventador Vice Crime City! Explore an open world with missions, upgrades, and wild driving action.",
      "tags": [],
      "category": "Home",
      "rating": "",
      "play_count": "",
      "game_type": "HTML5",
      "thumbnail": "https://www.onlinegames.io/media/posts/1048/aventador_vice_crime_city_game-2.webp",
      "thumbnail_alt": ""
    },
    {
      "title": "Basketball Stars",
      "url": "https://www.onlinegames.io/basketball-stars/",
      "iframes": [
        {
          "src": "https://www.onlinegames.io/games/2024/gm/basketball-stars/index.html",
          "width": "1060",
          "height": "650",
          "frameborder": "0",
          "allowfullscreen": "allowfullscreen",
          "sandbox": ""
        }
      ],
      "description": "Basketball Stars is a free online basketball game that you can enjoy on your browser. Start strong, and show your…",
      "tags": [],
      "category": "Home",
      "rating": "",
      "play_count": "",
      "game_type": "Web",
      "thumbnail": "https://www.onlinegames.io/media/posts/380/Basketball-Stars-Game.jpg",
      "thumbnail_alt": ""
    },
    {
      "title": "Paper io 2",
      "url": "https://www.onlinegames.io/paper-io-2/",
      "iframes": [
        {
          "src": "https://html5.gamedistribution.com/rvvASMiM/c5d4966b176246748d6c847103ebfd51/?gd_sdk_referrer_url=https://www.onlinegames.io/Paper-io-2",
          "width": "1060",
          "height": "650",
          "frameborder": "0",
          "allowfullscreen": "allowfullscreen",
          "sandbox": ""
        }
      ],
      "description": "Welcome to the colorful world of Paper io 2! Paper io 2 is a free online game where you have…",
      "tags": [],
      "category": "Home",
      "rating": "",
      "play_count": "",
      "game_type": "HTML5",
      "thumbnail": "https://www.onlinegames.io/media/posts/395/Paper-io-2-Online.jpg",
      "thumbnail_alt": ""
    },
    {
      "title": "Crazy Plane Landing",
      "url": "https://www.onlinegames.io/crazy-plane-landing/",
      "iframes": [
        {
          "src": "https://html5.gamedistribution.com/fd8ad948b534420caced19c62764019f/?gd_sdk_referrer_url=https://www.onlinegames.io/crazy-plane-landing/",
          "width": "1060",
          "height": "650",
          "frameborder": "0",
          "allowfullscreen": "allowfullscreen",
          "sandbox": ""
        }
      ],
      "description": "Crazy Plane Landing is a free online stunt game where you launch, boost, and steer a plane across wild 3D maps. Play now on OnlineGames.io!",
      "tags": [],
      "category": "Home",
      "rating": "",
      "play_count": "",
      "game_type": "HTML5",
      "thumbnail": "https://www.onlinegames.io/media/posts/999/crazy-plane-landing.jpg",
      "thumbnail_alt": ""
    },
    {
      "title": "Granny",
      "url": "https://www.onlinegames.io/granny/",
      "iframes": [
        {
          "src": "https://playhop.com/app/307198?utm_source=distrib&is-united-page=1&skip-guard=1&header=no&utm_medium=cristian-ovidiu&clid=8531463",
          "width": "1060",
          "height": "650",
          "frameborder": "0",
          "allowfullscreen": "allowfullscreen",
          "sandbox": ""
        }
      ],
      "description": "Trapped in Granny's eerie house, you must outsmart her razor-sharp hearing and escape before it's too late. Can you survive the scary puzzle game online?",
      "tags": [],
      "category": "Home",
      "rating": "",
      "play_count": "",
      "game_type": "Web",
      "thumbnail": "https://www.onlinegames.io/media/posts/884/granny.jpg",
      "thumbnail_alt": ""
    },
    {
      "title": "Minecraft Classic",
      "url": "https://www.onlinegames.io/minecraft-classic/",
      "iframes": [
        {
          "src": "https://cloud.onlinegames.io/games/2025/html/pixelmon-town/index.html",
          "width": "1060",
          "height": "650",
          "frameborder": "0",
          "allowfullscreen": "allowfullscreen",
          "sandbox": ""
        }
      ],
      "description": "Minecraft Classic is filled with so many details, options, and features that you won't miss any feature of the original game.Â Start building blocks now!",
      "tags": [],
      "category": "Home",
      "rating": "",
      "play_count": "",
      "game_type": "Web",
      "thumbnail": "https://www.onlinegames.io/media/posts/382/Minecraft-Classic-Game.jpg",
      "thumbnail_alt": ""
    },
    {
      "title": "Motorbike Stunt Simulator",
      "url": "https://www.onlinegames.io/motorbike-stunt-simulator/",
      "iframes": [
        {
          "src": "https://cloud.onlinegames.io/games/2021/unity/motorbike-stunt-simulator/index-og.html",
          "width": "1060",
          "height": "650",
          "frameborder": "0",
          "allowfullscreen": "allowfullscreen",
          "sandbox": ""
        }
      ],
      "description": "Play Motorbike Stunt Simulator, a free 3D motorcycle game with insane stunts and epic maps. Master flips, jumps, and tricks in four thrilling arenas!",
      "tags": [],
      "category": "Home",
      "rating": "",
      "play_count": "",
      "game_type": "Unity",
      "thumbnail": "https://www.onlinegames.io/media/posts/1045/motorbike_stunt_simulator_game-2.webp",
      "thumbnail_alt": ""
    },
    {
      "title": "Drift Hunters",
      "url": "https://www.onlinegames.io/drift-hunters/",
      "iframes": [
        {
          "src": "https://www.onlinegames.io/games/2023/unity3/drift-hunters/index.html",
          "width": "1060",
          "height": "650",
          "frameborder": "0",
          "allowfullscreen": "allowfullscreen",
          "sandbox": ""
        }
      ],
      "description": "Drift Hunters, a thrilling drift game, offers you a variety of sports cars and race tracks to burn your tires on the curved roads!",
      "tags": [],
      "category": "Home",
      "rating": "",
      "play_count": "",
      "game_type": "Unity",
      "thumbnail": "https://www.onlinegames.io/media/posts/637/Drift-Hunters-Game.jpg",
      "thumbnail_alt": ""
    },
    {
      "title": "Five Nights At Freddy's 2",
      "url": "https://www.onlinegames.io/five-nights-at-freddys-2/",
      "iframes": [
        {
          "src": "https://www.onlinegames.io/games/2024/w1/five-nights-at-freddys-2/index.html",
          "width": "1060",
          "height": "650",
          "frameborder": "0",
          "allowfullscreen": "allowfullscreen",
          "sandbox": ""
        }
      ],
      "description": "Five Nights at Freddy's 2 (FNaF 2) is a popular horror game with a spooky environment and a thrilling narrative. If you have the courage for it, play it now for free on OnlineGames.io!",
      "tags": [],
      "category": "Home",
      "rating": "",
      "play_count": "",
      "game_type": "Web",
      "thumbnail": "https://www.onlinegames.io/media/posts/771/FNaF-2.jpg",
      "thumbnail_alt": ""
    },
    {
      "title": "Sprunki",
      "url": "https://www.onlinegames.io/sprunki/",
      "iframes": [
        {
          "src": "https://cloud.onlinegames.io/games/2024/more2/sprunki/index.html",
          "width": "1060",
          "height": "650",
          "frameborder": "0",
          "allowfullscreen": "allowfullscreen",
          "sandbox": ""
        }
      ],
      "description": "Create haunting soundscapes with Sprunki! Mix beats, melodies, and vocals using quirky characters in this surreal music game. Play free online!",
      "tags": [],
      "category": "Home",
      "rating": "",
      "play_count": "",
      "game_type": "Web",
      "thumbnail": "https://www.onlinegames.io/media/posts/911/Sprunki.jpg",
      "thumbnail_alt": ""
    },
    {
      "title": "Smash Karts",
      "url": "https://www.onlinegames.io/smash-karts/",
      "iframes": [
        {
          "src": "https://smashkarts.io/",
          "width": "1060",
          "height": "650",
          "frameborder": "0",
          "allowfullscreen": "allowfullscreen",
          "sandbox": ""
        }
      ],
      "description": "Smash Karts is a 3D multiplayer go-kart battle game where you drive on wacky maps and smash other karts! ",
      "tags": [],
      "category": "Home",
      "rating": "",
      "play_count": "",
      "game_type": "Web",
      "thumbnail": "https://www.onlinegames.io/media/posts/373/smash-karts-online.jpg",
      "thumbnail_alt": ""
    },
    {
      "title": "Fast Food Rush",
      "url": "https://www.onlinegames.io/fast-food-rush/",
      "iframes": [
        {
          "src": "https://cloud.onlinegames.io/games/2025/unity/fast-food-rush/index-og.html",
          "width": "1060",
          "height": "650",
          "frameborder": "0",
          "allowfullscreen": "allowfullscreen",
          "sandbox": ""
        }
      ],
      "description": "Play Fast Food Rush online and run your own restaurant . Start with selling burgers, unlock coffee and donuts, hire workers, and upgrade!",
      "tags": [],
      "category": "Home",
      "rating": "",
      "play_count": "",
      "game_type": "Unity",
      "thumbnail": "https://www.onlinegames.io/media/posts/979/fast-food-rush.jpg",
      "thumbnail_alt": ""
    },
    {
      "title": "DTA 6",
      "url": "https://www.onlinegames.io/dta-6/",
      "iframes": [
        {
          "src": "https://playhop.com/app/285639?utm_source=distrib&is-united-page=1&skip-guard=1&header=no&utm_medium=cristian-ovidiu&clid=8531463",
          "width": "1060",
          "height": "650",
          "frameborder": "0",
          "allowfullscreen": "allowfullscreen",
          "sandbox": ""
        }
      ],
      "description": "Play DTA 6, a free online game where you explore a city, commit crimes, and outrun the cops as Jack, the gang member.",
      "tags": [],
      "category": "Home",
      "rating": "",
      "play_count": "",
      "game_type": "Web",
      "thumbnail": "https://www.onlinegames.io/media/posts/906/dta-6-online.jpg",
      "thumbnail_alt": ""
    },
    {
      "title": "Spacebar Clicker",
      "url": "https://www.onlinegames.io/spacebar-clicker/",
      "iframes": [
        {
          "src": "https://www.onlinegames.io/games/2024/more/spacebar-clicker/index.html",
          "width": "1060",
          "height": "650",
          "frameborder": "0",
          "allowfullscreen": "allowfullscreen",
          "sandbox": ""
        }
      ],
      "description": "Spacebar Clicker is a 2D clicker game that requires you to tap on the spacebar key. To get the highest figures, you will need monkeys and boomer moms!",
      "tags": [],
      "category": "Home",
      "rating": "",
      "play_count": "",
      "game_type": "Web",
      "thumbnail": "https://www.onlinegames.io/media/posts/684/Spacebar-Clicker.jpg",
      "thumbnail_alt": ""
    },
    {
      "title": "Stick Fighter 3D",
      "url": "https://www.onlinegames.io/stick-fighter-3d/",
      "iframes": [
        {
          "src": "https://cloud.onlinegames.io/games/2024/gm/games3/stick-fighter-3d/index.html",
          "width": "1060",
          "height": "650",
          "frameborder": "0",
          "allowfullscreen": "allowfullscreen",
          "sandbox": ""
        }
      ],
      "description": "Play Stick Fighter 3D online now and settle the score!",
      "tags": [],
      "category": "Home",
      "rating": "",
      "play_count": "",
      "game_type": "Web",
      "thumbnail": "https://www.onlinegames.io/media/posts/1026/stick-fighter-3d.jpg",
      "thumbnail_alt": ""
    },
    {
      "title": "Hexanaut io",
      "url": "https://www.onlinegames.io/hexanaut-io/",
      "iframes": [
        {
          "src": "https://hexanaut.io/",
          "width": "1060",
          "height": "650",
          "frameborder": "0",
          "allowfullscreen": "allowfullscreen",
          "sandbox": ""
        }
      ],
      "description": "Get ready to be an expansionist, conquer and defend your territory in Hexanaut io! Hexanaut io is an online browser…",
      "tags": [],
      "category": "Home",
      "rating": "",
      "play_count": "",
      "game_type": "Web",
      "thumbnail": "https://www.onlinegames.io/media/posts/394/Hexanaut-io.jpg",
      "thumbnail_alt": ""
    },
    {
      "title": "Survival Race",
      "url": "https://www.onlinegames.io/survival-race/",
      "iframes": [
        {
          "src": "https://playhop.com/app/288720?utm_source=distrib&is-united-page=1&skip-guard=1&header=no&utm_medium=cristian-ovidiu&clid=8531463",
          "width": "1060",
          "height": "650",
          "frameborder": "0",
          "allowfullscreen": "allowfullscreen",
          "sandbox": ""
        }
      ],
      "description": "Survival Race, is a 3D car racing game that offers a unique racing experience and has a special place in the hearts of web gamers. ",
      "tags": [],
      "category": "Home",
      "rating": "",
      "play_count": "",
      "game_type": "Web",
      "thumbnail": "https://www.onlinegames.io/media/posts/768/Survival-Race.jpg",
      "thumbnail_alt": ""
    },
    {
      "title": "Capybara Clicker Pro",
      "url": "https://www.onlinegames.io/capybara-clicker-pro/",
      "iframes": [
        {
          "src": "https://www.onlinegames.io/games/2023/q2/capybara-clicker-pro/index.html",
          "width": "1060",
          "height": "650",
          "frameborder": "0",
          "allowfullscreen": "allowfullscreen",
          "sandbox": ""
        }
      ],
      "description": "The more coins you earn in the Capybara Clicker Pro game, the better! Click on the sweet creature and earn coins for him.",
      "tags": [],
      "category": "Home",
      "rating": "",
      "play_count": "",
      "game_type": "Web",
      "thumbnail": "https://www.onlinegames.io/media/posts/554/Capybara-Clicker-Pro.jpg",
      "thumbnail_alt": ""
    },
    {
      "title": "Flappy Bird",
      "url": "https://www.onlinegames.io/flappy-bird/",
      "iframes": [
        {
          "src": "https://cloud.onlinegames.io/games/2025/html/flappy-bird/index-og.html",
          "width": "1060",
          "height": "650",
          "frameborder": "0",
          "allowfullscreen": "allowfullscreen",
          "sandbox": ""
        }
      ],
      "description": "Play Flappy Bird online for free! Tap to fly, avoid pipes, earn medals, and relive the classic arcade challenge. No download needed.",
      "tags": [],
      "category": "Home",
      "rating": "",
      "play_count": "",
      "game_type": "Web",
      "thumbnail": "https://www.onlinegames.io/media/posts/1049/flappy_bird_game.webp",
      "thumbnail_alt": ""
    },
    {
      "title": "Escape Car",
      "url": "https://www.onlinegames.io/escape-car/",
      "iframes": [
        {
          "src": "https://cloud.onlinegames.io/games/2025/unity2/escape-car/index-og.html",
          "width": "1060",
          "height": "650",
          "frameborder": "0",
          "allowfullscreen": "allowfullscreen",
          "sandbox": ""
        }
      ],
      "description": "Play Escape Car free online , an easy-to-pick-up 3D police chase game. Drift past cops, grab cash, unlock new cars, and see how long you can stay free!",
      "tags": [],
      "category": "Home",
      "rating": "",
      "play_count": "",
      "game_type": "Unity",
      "thumbnail": "https://www.onlinegames.io/media/posts/1000/Escape-Car.jpg",
      "thumbnail_alt": ""
    },
    {
      "title": "Madalin Stunt Cars Pro",
      "url": "https://www.onlinegames.io/madalin-stunt-cars-pro/",
      "iframes": [
        {
          "src": "https://www.onlinegames.io/games/2023/unity/madalin-stunt-cars-pro/index.html",
          "width": "1060",
          "height": "650",
          "frameborder": "0",
          "allowfullscreen": "allowfullscreen",
          "sandbox": ""
        }
      ],
      "description": "Are you open to experiencing luxury? The 3D driving game Madalin Stunt Cars Pro features excellent graphics for lifelike experiences.",
      "tags": [],
      "category": "Home",
      "rating": "",
      "play_count": "",
      "game_type": "Unity",
      "thumbnail": "https://www.onlinegames.io/media/posts/401/Madalin-Stunt-Cars-Pro-Game.jpg",
      "thumbnail_alt": ""
    },
    {
      "title": "Stickman Parkour",
      "url": "https://www.onlinegames.io/stickman-parkour/",
      "iframes": [
        {
          "src": "https://cloud.onlinegames.io/games/2024/construct/219/stickman-parkour/index-og.html",
          "width": "1060",
          "height": "650",
          "frameborder": "0",
          "allowfullscreen": "allowfullscreen",
          "sandbox": ""
        }
      ],
      "description": "Stickman Parkour is a platformer game full of action! Play it online for free on OnlineGames.io!",
      "tags": [],
      "category": "Home",
      "rating": "",
      "play_count": "",
      "game_type": "Web",
      "thumbnail": "https://www.onlinegames.io/media/posts/871/stickman-parkour-OG.jpg",
      "thumbnail_alt": ""
    },
    {
      "title": "Stickman GTA City",
      "url": "https://www.onlinegames.io/stickman-gta-city/",
      "iframes": [
        {
          "src": "https://cloud.onlinegames.io/games/2024/unity3/stickman-gta-city/index-og.html",
          "width": "1060",
          "height": "650",
          "frameborder": "0",
          "allowfullscreen": "allowfullscreen",
          "sandbox": ""
        }
      ],
      "description": "Explore Stickman GTA City, an open-world game where you steal vehicles, evade police, and take on missions with stickman twist. Play now for free!",
      "tags": [],
      "category": "Home",
      "rating": "",
      "play_count": "",
      "game_type": "Unity",
      "thumbnail": "https://www.onlinegames.io/media/posts/900/stickman-gta-city-free.jpg",
      "thumbnail_alt": ""
    },
    {
      "title": "Red Light Green Light",
      "url": "https://www.onlinegames.io/red-light-green-light/",
      "iframes": [
        {
          "src": "https://html5.gamedistribution.com/788f89d325d840f391139ce0e1212c46/?gd_sdk_referrer_url=https://www.onlinegames.io/red-light-green-light/",
          "width": "1060",
          "height": "650",
          "frameborder": "0",
          "allowfullscreen": "allowfullscreen",
          "sandbox": ""
        }
      ],
      "description": "Play Squid Race Simulator online, a video game inspired by Red Light, Green Light of Squid Game! ",
      "tags": [],
      "category": "Home",
      "rating": "",
      "play_count": "",
      "game_type": "HTML5",
      "thumbnail": "https://www.onlinegames.io/media/posts/1017/red-light-green-light.jpg",
      "thumbnail_alt": ""
    },
    {
      "title": "Get On Top",
      "url": "https://www.onlinegames.io/get-on-top/",
      "iframes": [
        {
          "src": "https://www.onlinegames.io/games/2024/code/6/get-on-top/index.html",
          "width": "1060",
          "height": "650",
          "frameborder": "0",
          "allowfullscreen": "allowfullscreen",
          "sandbox": ""
        }
      ],
      "description": "Get on Top is a 2-player stickman game where players combat with a friend, trying to get on top and make the opponent's head touch the ground.",
      "tags": [],
      "category": "Home",
      "rating": "",
      "play_count": "",
      "game_type": "Web",
      "thumbnail": "https://www.onlinegames.io/media/posts/697/Get-on-Top.jpg",
      "thumbnail_alt": ""
    },
    {
      "title": "Pacman 30th Anniversary",
      "url": "https://www.onlinegames.io/google-pacman/",
      "iframes": [
        {
          "src": "https://www.onlinegames.io/games/2024/more/tapman/index.html",
          "width": "1060",
          "height": "650",
          "frameborder": "0",
          "allowfullscreen": "allowfullscreen",
          "sandbox": ""
        }
      ],
      "description": "The world's most-known game, Pac-Man, is released as a Google Doodle to celebrate the 30th Anniversary of the game's initial release. Play now on OnlineGames.io",
      "tags": [],
      "category": "Home",
      "rating": "",
      "play_count": "",
      "game_type": "Web",
      "thumbnail": "https://www.onlinegames.io/media/posts/641/Pac-Man-30th-Anniversary.jpg",
      "thumbnail_alt": ""
    },
    {
      "title": "FPS Simulator",
      "url": "https://www.onlinegames.io/fps-simulator/",
      "iframes": [
        {
          "src": "https://www.onlinegames.io/games/2023/unity3/fps-simulator/index.html",
          "width": "1060",
          "height": "650",
          "frameborder": "0",
          "allowfullscreen": "allowfullscreen",
          "sandbox": ""
        }
      ],
      "description": "Grab your sniper rifle, climb up the ladders and crouch! Take your enemies down one by one in the action game FPS Simulator.",
      "tags": [],
      "category": "Home",
      "rating": "",
      "play_count": "",
      "game_type": "Unity",
      "thumbnail": "https://www.onlinegames.io/media/posts/680/Fps-simulator.jpg",
      "thumbnail_alt": ""
    },
    {
      "title": "Gulper io",
      "url": "https://www.onlinegames.io/gulper-io/",
      "iframes": [
        {
          "src": "https://gulper.io/",
          "width": "1060",
          "height": "650",
          "frameborder": "0",
          "allowfullscreen": "allowfullscreen",
          "sandbox": ""
        }
      ],
      "description": "As a gulper, you will participate in snake wars in the multiplayer snake game Gulper io. Take all the pellets on the ground and get bigger!",
      "tags": [],
      "category": "Home",
      "rating": "",
      "play_count": "",
      "game_type": "Web",
      "thumbnail": "https://www.onlinegames.io/media/posts/660/Gulper-io.jpg",
      "thumbnail_alt": ""
    },
    {
      "title": "City Police Cars",
      "url": "https://www.onlinegames.io/city-police-cars/",
      "iframes": [
        {
          "src": "https://cloud.onlinegames.io/games/2021/2/city-police-cars/index-og.html",
          "width": "1060",
          "height": "650",
          "frameborder": "0",
          "allowfullscreen": "allowfullscreen",
          "sandbox": ""
        }
      ],
      "description": "Play City Police Cars, a fast-paced 2D action game where you drive and take down criminals. Collect coins, upgrade vehicles, and conquer 30 exciting levels. ",
      "tags": [],
      "category": "Home",
      "rating": "",
      "play_count": "",
      "game_type": "Web",
      "thumbnail": "https://www.onlinegames.io/media/posts/1053/city_police_cars_game-4.webp",
      "thumbnail_alt": ""
    },
    {
      "title": "Futuristic Racer",
      "url": "https://www.onlinegames.io/futuristic-racer/",
      "iframes": [
        {
          "src": "https://cloud.onlinegames.io/games/2021/2/futuristic-racer/index-og.html",
          "width": "1060",
          "height": "650",
          "frameborder": "0",
          "allowfullscreen": "allowfullscreen",
          "sandbox": ""
        }
      ],
      "description": "Race through 30 neon-lit levels in Futuristic Racer! Collect gems, unlock cars, and master nitro-fueled speed in this high-tech, fast-paced racing game.",
      "tags": [],
      "category": "Home",
      "rating": "",
      "play_count": "",
      "game_type": "Web",
      "thumbnail": "https://www.onlinegames.io/media/posts/1051/futuristic_racer_game.webp",
      "thumbnail_alt": ""
    },
    {
      "title": "Wood Block Jam",
      "url": "https://www.onlinegames.io/wood-block-jam/",
      "iframes": [
        {
          "src": "https://html5.gamedistribution.com/678f54b0c203460b8f8916a239a28bff/?gd_sdk_referrer_url=https://www.onlinegames.io/wood-block-jam/",
          "width": "1060",
          "height": "650",
          "frameborder": "0",
          "allowfullscreen": "allowfullscreen",
          "sandbox": ""
        }
      ],
      "description": "Slide, think, and solve in Wood Block Jam, a colorful puzzle game where every move counts. Easy to play, hard to master. Can you beat the grid?",
      "tags": [],
      "category": "Home",
      "rating": "",
      "play_count": "",
      "game_type": "HTML5",
      "thumbnail": "https://www.onlinegames.io/media/posts/1054/wood_block_jam_game.webp",
      "thumbnail_alt": ""
    },
    {
      "title": "Crazy Strike Force",
      "url": "https://www.onlinegames.io/crazy-strike-force/",
      "iframes": [
        {
          "src": "https://www.onlinegames.io/games/2023/unity/crazy-strike-force/index.html",
          "width": "1060",
          "height": "650",
          "frameborder": "0",
          "allowfullscreen": "allowfullscreen",
          "sandbox": ""
        }
      ],
      "description": "Join the ultimate battle competition in the Crazy Strike Force game. You can customize your character with a unique style…",
      "tags": [],
      "category": "Home",
      "rating": "",
      "play_count": "",
      "game_type": "Unity",
      "thumbnail": "https://www.onlinegames.io/media/posts/366/Crazy-Strike-Force.jpg",
      "thumbnail_alt": ""
    },
    {
      "title": "Police Chase Drifter",
      "url": "https://www.onlinegames.io/police-chase-drifter/",
      "iframes": [
        {
          "src": "https://www.onlinegames.io/games/2021/3/police-chase-drifter/index.html",
          "width": "1060",
          "height": "650",
          "frameborder": "0",
          "allowfullscreen": "allowfullscreen",
          "sandbox": ""
        }
      ],
      "description": "Collect money and ride with speed while escaping the police cars. Police Chase Drifter will give you the chance to…",
      "tags": [],
      "category": "Home",
      "rating": "",
      "play_count": "",
      "game_type": "Web",
      "thumbnail": "https://www.onlinegames.io/media/posts/155/Police-Chase-Drifter-Online.jpg",
      "thumbnail_alt": ""
    },
    {
      "title": "Obby Tower Parkour Climb",
      "url": "https://www.onlinegames.io/obby-tower-parkour-climb/",
      "iframes": [
        {
          "src": "https://html5.gamedistribution.com/5532111b774e4ca18238b41c029617e0/?gd_sdk_referrer_url=https://www.onlinegames.io/obby-tower-parkour-climb/",
          "width": "1060",
          "height": "650",
          "frameborder": "0",
          "allowfullscreen": "allowfullscreen",
          "sandbox": ""
        }
      ],
      "description": "Play Obby Tower Parkour Climb and master parkour skills in a Roblox-inspired adventure. Climb towers, beat times, and challenge friends!",
      "tags": [],
      "category": "Home",
      "rating": "",
      "play_count": "",
      "game_type": "HTML5",
      "thumbnail": "https://www.onlinegames.io/media/posts/943/obby-tower-parkour-climb.jpg",
      "thumbnail_alt": ""
    },
    {
      "title": "Basket Random",
      "url": "https://www.onlinegames.io/basket-random/",
      "iframes": [
        {
          "src": "https://html5.gamedistribution.com/bf1268dccb5d43e7970bb3edaa54afc8/?gd_sdk_referrer_url=https://www.onlinegames.io/basket-random",
          "width": "1060",
          "height": "650",
          "frameborder": "0",
          "allowfullscreen": "allowfullscreen",
          "sandbox": ""
        }
      ],
      "description": "Basket Random is a basketball game in which everything changes randomly in each match. Score baskets and beat your opponents, whether a CPU or a friend.",
      "tags": [],
      "category": "Home",
      "rating": "",
      "play_count": "",
      "game_type": "HTML5",
      "thumbnail": "https://www.onlinegames.io/media/posts/651/Basket-Random.jpg",
      "thumbnail_alt": ""
    },
    {
      "title": "Cube Worlds",
      "url": "https://www.onlinegames.io/cube-worlds/",
      "iframes": [
        {
          "src": "https://cloud.onlinegames.io/games/2025/html/cube-worlds/index-og.html",
          "width": "1060",
          "height": "650",
          "frameborder": "0",
          "allowfullscreen": "allowfullscreen",
          "sandbox": ""
        }
      ],
      "description": "Play Cube Worlds online for free! Perfect Minecraft game to play on your browser!",
      "tags": [],
      "category": "Home",
      "rating": "",
      "play_count": "",
      "game_type": "Web",
      "thumbnail": "https://www.onlinegames.io/media/posts/986/Cube-Worlds.jpg",
      "thumbnail_alt": ""
    },
    {
      "title": "Drift Rider",
      "url": "https://www.onlinegames.io/drift-rider/",
      "iframes": [
        {
          "src": "https://www.onlinegames.io/games/2023/unity3/drift-rider/index.html",
          "width": "1060",
          "height": "650",
          "frameborder": "0",
          "allowfullscreen": "allowfullscreen",
          "sandbox": ""
        }
      ],
      "description": "Precise drifting is the main objective of the drift game Drift Rider. Get your car strengthened, customized, and ready to go!",
      "tags": [],
      "category": "Home",
      "rating": "",
      "play_count": "",
      "game_type": "Unity",
      "thumbnail": "https://www.onlinegames.io/media/posts/553/Drift-Rider.jpg",
      "thumbnail_alt": ""
    },
    {
      "title": "Fireboy and Watergirl",
      "url": "https://www.onlinegames.io/fireboy-and-watergirl/",
      "iframes": [
        {
          "src": "https://html5.gamedistribution.com/a55c9cc9c21e4fc683c8c6857f3d0c75/?gd_sdk_referrer_url=https://www.onlinegames.io/fireboy-and-watergirl",
          "width": "1060",
          "height": "650",
          "frameborder": "0",
          "allowfullscreen": "allowfullscreen",
          "sandbox": ""
        }
      ],
      "description": "Have you heard the saying 'Opposites attract'? We want to introduce you two best friends that can never be together:Â Fireboy…",
      "tags": [],
      "category": "Home",
      "rating": "",
      "play_count": "",
      "game_type": "HTML5",
      "thumbnail": "https://www.onlinegames.io/media/posts/377/Fireboy-and-Watergirl-Online.jpg",
      "thumbnail_alt": ""
    },
    {
      "title": "Jacksmith",
      "url": "https://www.onlinegames.io/jacksmith/",
      "iframes": [
        {
          "src": "https://cloud.onlinegames.io/games/2024/flash/jacksmith/index-og.html",
          "width": "1060",
          "height": "650",
          "frameborder": "0",
          "allowfullscreen": "allowfullscreen",
          "sandbox": ""
        }
      ],
      "description": "Forge epic weapons, aid warriors in battle, and defeat magical enemies in Jacksmith, the action-packed blacksmithing game you can play online for free!",
      "tags": [],
      "category": "Home",
      "rating": "",
      "play_count": "",
      "game_type": "Flash",
      "thumbnail": "https://www.onlinegames.io/media/posts/1055/jacksmith-online-game.webp",
      "thumbnail_alt": ""
    },
    {
      "title": "LOLbeans io",
      "url": "https://www.onlinegames.io/lolbeans-io/",
      "iframes": [
        {
          "src": "https://lolbeans.io/",
          "width": "1060",
          "height": "650",
          "frameborder": "0",
          "allowfullscreen": "allowfullscreen",
          "sandbox": ""
        }
      ],
      "description": "LOLbeans io is an online BR platformer game with funny and colorful visuals. Start running and try to reach the finish line!",
      "tags": [],
      "category": "Home",
      "rating": "",
      "play_count": "",
      "game_type": "Web",
      "thumbnail": "https://www.onlinegames.io/media/posts/388/Lolbeans-io-Play.jpg",
      "thumbnail_alt": ""
    }
  ]
}